{
  "d75fa5875ff1464497e5c2191ee803b9": [
    {
      "window": {
        "heading": -0.7035487292662879,
        "distance": 0.5599692310932605
      }
    },
    {},
    {},
    {},
    {},
    {
      "shelf cabinet shelf cabinet": {
        "heading": 165.51675643271244,
        "distance": 1.0804005150087812
      }
    },
    {
      "mattress": {
        "heading": -29.043107934499403,
        "distance": 0.6040123218694531
      }
    },
    {
      "footstool ottoman": {
        "heading": 7.259419100964976,
        "distance": 1.7945275201747595
      }
    },
    {
      "stairs": {
        "heading": 4.605721028887473,
        "distance": 1.280655926987416
      }
    },
    {},
    {},
    {
      "picture picture frame": {
        "heading": 44.1692636725364,
        "distance": 1.9275618376969548
      }
    },
    {
      "pool": {
        "heading": 0.07644360522334637,
        "distance": 1.998285484042959
      }
    },
    {
      "picture picture frame": {
        "heading": -168.95973769328268,
        "distance": 1.8972140153425667
      }
    },
    {},
    {},
    {
      "bed": {
        "heading": -89.3283993819848,
        "distance": 1.6064109205376333
      }
    },
    {
      "bed": {
        "heading": -49.32866597320859,
        "distance": 1.1972661107523173
      }
    },
    {},
    {
      "footstool ottoman": {
        "heading": 75.79289807110402,
        "distance": 1.4384307242053984
      }
    },
    {},
    {},
    {
      "lamp": {
        "heading": -62.08723978255212,
        "distance": 1.2117560123553572
      }
    },
    {
      "window": {
        "heading": 49.119005699392886,
        "distance": 1.1007728455017243
      }
    },
    {},
    {},
    {}
  ],
  "8eacf8672d1546f6b90a6966b6e45db0": [
    {},
    {},
    {
      "shelf cabinet shelf cabinet": {
        "heading": 124.12337493639075,
        "distance": 1.6397077042914363
      }
    },
    {
      "door closet": {
        "heading": -75.67216689844096,
        "distance": 0.6646073476627308
      }
    },
    {},
    {},
    {
      "stairs": {
        "heading": -161.32045577929944,
        "distance": 0.6317196185588201
      }
    },
    {},
    {},
    {
      "door closet": {
        "heading": 107.41934486823726,
        "distance": 0.7463541921703951
      }
    },
    {},
    {
      "picture picture frame": {
        "heading": -158.36938963790362,
        "distance": 1.2405729860373376
      }
    },
    {
      "shelf cabinet shelf cabinet": {
        "heading": -83.9454590043111,
        "distance": 1.4131119315641063
      }
    },
    {},
    {
      "couch sofa sofa": {
        "heading": -147.51116689898154,
        "distance": 1.8367312585920366
      }
    },
    {
      "stove grill": {
        "heading": -112.2229809383869,
        "distance": 1.3239633874651349
      }
    },
    {
      "grill": {
        "heading": 63.42859824138708,
        "distance": 1.2559944205930522
      }
    }
  ],
  "95a7711cf04e4681858182530de24d12": [
    {
      "towel towel rack": {
        "heading": -143.41576368255232,
        "distance": 0.6723675860126528
      }
    },
    {
      "towel": {
        "heading": 85.28887403139646,
        "distance": 1.0210603805291538
      }
    },
    {
      "pillow": {
        "heading": -127.34276128311885,
        "distance": 1.2165333966772276
      }
    },
    {
      "pillow": {
        "heading": 17.39896359451413,
        "distance": 1.4949133551137788
      }
    },
    {},
    {},
    {
      "towel": {
        "heading": 42.083111654659064,
        "distance": 1.933479511658366
      }
    },
    {
      "mirror": {
        "heading": 44.57625646568931,
        "distance": 1.4172968508322799
      }
    },
    {},
    {
      "mattress": {
        "heading": -80.23508434915252,
        "distance": 0.6198921243014324
      }
    },
    {
      "window": {
        "heading": 149.37844209448048,
        "distance": 1.1159228316551877
      }
    },
    {},
    {
      "towel": {
        "heading": -133.52259898189695,
        "distance": 1.7829773885079787
      }
    },
    {},
    {},
    {},
    {},
    {
      "door closet": {
        "heading": 24.265881627322273,
        "distance": 0.8790427530771738
      }
    },
    {},
    {
      "door closet": {
        "heading": 119.09224894649162,
        "distance": 1.770463923864677
      }
    },
    {},
    {
      "rug pool mattress": {
        "heading": -178.51321455430764,
        "distance": 0.6835556334339745
      }
    },
    {
      "desk": {
        "heading": 14.875050770887583,
        "distance": 1.9382622978548172
      }
    },
    {},
    {},
    {
      "shelf cabinet shelf cabinet dresser": {
        "heading": 145.2488729288358,
        "distance": 1.7767497319856018
      }
    },
    {
      "bed": {
        "heading": -134.73025665896773,
        "distance": 0.5042442683588538
      }
    },
    {
      "bed": {
        "heading": 1.267317006068339,
        "distance": 1.3634102054182544
      }
    }
  ],
  "50e6b50f81554912a305b166a0fd1a85": [
    {
      "couch sofa sofa": {
        "heading": -36.93548799616721,
        "distance": 1.419640728391958
      }
    },
    {
      "couch sofa sofa": {
        "heading": -104.25116753013464,
        "distance": 1.6749559195316626
      }
    },
    {},
    {},
    {
      "door": {
        "heading": 41.57460981879743,
        "distance": 0.5003952246383028
      }
    },
    {},
    {},
    {
      "chandelier chandelier": {
        "heading": -20.64152531183464,
        "distance": 1.624050914463617
      }
    },
    {},
    {
      "pillow": {
        "heading": 87.7691599476803,
        "distance": 1.1333660470124858
      }
    },
    {},
    {},
    {}
  ],
  "157ae59bfdf04cf5ba5785dde25b039e": [
    {},
    {
      "couch sofa sofa": {
        "heading": -118.09709732206119,
        "distance": 1.9101611675019299
      }
    },
    {},
    {},
    {},
    {},
    {},
    {},
    {},
    {},
    {},
    {},
    {},
    {},
    {},
    {},
    {
      "door": {
        "heading": -132.9458198083937,
        "distance": 0.6213623272288105
      }
    }
  ],
  "0aa7d38c4a904859b548bd69f4691106": [
    {
      "stairs": {
        "heading": -21.66910845440657,
        "distance": 1.6537857835628929
      }
    },
    {},
    {},
    {},
    {},
    {
      "picture picture frame": {
        "heading": -36.2008394079086,
        "distance": 1.383361566677055
      }
    },
    {},
    {},
    {
      "window": {
        "heading": 21.414968546068025,
        "distance": 1.993440392031089
      }
    },
    {},
    {},
    {},
    {},
    {},
    {
      "window": {
        "heading": 117.78686954645678,
        "distance": 1.5458033617958793
      }
    },
    {},
    {},
    {
      "shelf cabinet shelf cabinet dresser": {
        "heading": -21.30170208556578,
        "distance": 0.7596154194244563
      }
    },
    {},
    {},
    {},
    {}
  ],
  "b2e6464d05eb49c69144ff197c24db72": [
    {
      "rug mattress": {
        "heading": -167.7311287811312,
        "distance": 1.899456289061473
      }
    },
    {
      "rug": {
        "heading": 69.32807407876226,
        "distance": 0.9985839882695415
      }
    },
    {},
    {},
    {
      "rug": {
        "heading": 80.8916970836612,
        "distance": 0.7613963503247267
      }
    },
    {},
    {},
    {
      "stool footsto": {
        "heading": 47.260250990987544,
        "distance": 1.748472141573357
      }
    },
    {},
    {},
    {},
    {
      "picture picture _ frame eye _ chart": {
        "heading": 163.04683249920748,
        "distance": 0.5788408700396002
      }
    },
    {
      "footstool ottoman": {
        "heading": -12.873603189293192,
        "distance": 1.8118445365448137
      }
    },
    {},
    {},
    {
      "rug": {
        "heading": 175.6237365466132,
        "distance": 1.4016890715161916
      }
    },
    {},
    {
      "stool foot ottoman": {
        "heading": 90.08372326202817,
        "distance": 0.9966227706089215
      }
    },
    {
      "picture picture frame": {
        "heading": -44.9453522771056,
        "distance": 1.577930279142824
      }
    },
    {},
    {},
    {},
    {},
    {},
    {
      "curtain": {
        "heading": 175.01137499678578,
        "distance": 0.5970223506394092
      }
    },
    {},
    {},
    {},
    {},
    {},
    {},
    {},
    {},
    {}
  ],
  "2e024b2658064f9099f0ffd136fc4a0a": [
    {},
    {
      "basket": {
        "heading": 62.83965138450043,
        "distance": 0.5279342355880301
      }
    },
    {
      "rug": {
        "heading": 139.82813972785164,
        "distance": 0.8667683249856026
      }
    },
    {
      "rug": {
        "heading": -64.21506954236676,
        "distance": 0.8094416958918861
      }
    },
    {},
    {
      "chandelier chandelier": {
        "heading": -123.58319164438691,
        "distance": 1.6736123358968236
      }
    },
    {
      "piano grill": {
        "heading": -28.50129283244155,
        "distance": 1.8507492054234003
      }
    },
    {
      "chandelier chandelier": {
        "heading": 56.62196549315013,
        "distance": 1.6283703826946303
      }
    },
    {},
    {},
    {},
    {
      "couch sofa sofa": {
        "heading": 55.42134685763685,
        "distance": 1.8174338369290752
      }
    },
    {
      "stool foot": {
        "heading": -115.21921433145701,
        "distance": 1.795033656206015
      }
    },
    {},
    {
      "rug": {
        "heading": -43.516905959947735,
        "distance": 1.8010405113366765
      }
    },
    {},
    {
      "window": {
        "heading": -63.32721269500908,
        "distance": 0.6260560074463528
      }
    },
    {
      "stool": {
        "heading": 133.3112229283522,
        "distance": 1.5116752470074144
      }
    },
    {},
    {},
    {
      "couch sofa seat sofa": {
        "heading": -172.70770995892408,
        "distance": 1.5365405137664103
      }
    },
    {
      "seat mattress ottoman": {
        "heading": 69.0918027278143,
        "distance": 1.1768419739084028
      }
    },
    {
      "rug": {
        "heading": 131.7864003259773,
        "distance": 0.7378687157260854
      }
    },
    {},
    {},
    {},
    {
      "window": {
        "heading": 61.113798408243554,
        "distance": 1.8662424926694265
      }
    },
    {},
    {
      "window": {
        "heading": -178.41046450226182,
        "distance": 1.9769597935879317
      }
    }
  ],
  "d9a5041cfe7042dcbd89101799e8bc8f": [
    {
      "fridge": {
        "heading": -76.36186246334576,
        "distance": 0.6021836588445849
      }
    },
    {},
    {
      "footstool ottoman": {
        "heading": 141.1821370161387,
        "distance": 1.1564064859703929
      }
    },
    {},
    {},
    {},
    {
      "grill": {
        "heading": -145.5919465909183,
        "distance": 1.2706632724168019
      }
    },
    {
      "oven": {
        "heading": -46.576063352398734,
        "distance": 1.5951049683376635
      }
    },
    {
      "shelf cabinet shelf cabinet": {
        "heading": -50.847745714901976,
        "distance": 1.8842519453158713
      }
    },
    {},
    {},
    {
      "shelf cabinet shelf cabinet": {
        "heading": 48.97573908618892,
        "distance": 0.6591556908264229
      }
    },
    {
      "stool footstool ottoman": {
        "heading": 37.14624973020861,
        "distance": 1.0765085273260087
      }
    },
    {
      "chair armchair seat armchair": {
        "heading": -7.889440911648592,
        "distance": 0.7519893693660994
      }
    },
    {},
    {
      "chair armchair armchair": {
        "heading": 87.8843794497443,
        "distance": 0.9117176481587621
      }
    },
    {},
    {
      "microwave": {
        "heading": 168.03688895643586,
        "distance": 0.712150955062962
      }
    }
  ],
  "bf428f443730499685d561a4221be040": [
    {},
    {},
    {},
    {
      "vent": {
        "heading": -117.71717803514319,
        "distance": 0.6790394442752012
      }
    },
    {},
    {},
    {},
    {
      "footstool ottoman": {
        "heading": 115.54550789842568,
        "distance": 1.6259632062529437
      }
    },
    {},
    {
      "door": {
        "heading": -92.81288593623545,
        "distance": 1.2320763554515188
      }
    },
    {},
    {},
    {
      "door closet": {
        "heading": 67.16869697216524,
        "distance": 1.688685290813027
      }
    },
    {},
    {
      "window": {
        "heading": -176.63161313336448,
        "distance": 1.4448735227588974
      }
    },
    {},
    {
      "eye _ chart console _ table plaque": {
        "heading": -137.31357518315116,
        "distance": 1.4073520135959772
      }
    },
    {},
    {},
    {},
    {},
    {},
    {},
    {
      "footstool": {
        "heading": -20.18762466147774,
        "distance": 1.4145239886373748
      }
    },
    {
      "closet": {
        "heading": 64.27299034518418,
        "distance": 1.1072006282236178
      }
    },
    {}
  ],
  "c18f83b284d041abba9a6afa23d2ebf8": [
    {
      "towel": {
        "heading": -83.5800358369024,
        "distance": 1.0119799062355637
      }
    },
    {
      "towel towel rack": {
        "heading": 65.26429477621605,
        "distance": 1.7212760250301162
      }
    },
    {},
    {
      "bed": {
        "heading": -67.05399442608342,
        "distance": 0.7467987533656814
      }
    },
    {
      "shelf cabinet shelf cabinet": {
        "heading": 99.95479821138872,
        "distance": 1.3138404125401677
      }
    },
    {
      "towel": {
        "heading": 0.8595186198298848,
        "distance": 1.8574101357836807
      }
    },
    {
      "footstool ottoman": {
        "heading": 14.266749042979768,
        "distance": 1.8705935446082969
      }
    },
    {},
    {
      "towel": {
        "heading": -113.91332164629934,
        "distance": 0.8627625868602435
      }
    },
    {},
    {},
    {
      "shelf cabinet bookcase shelf cabinet": {
        "heading": 161.23728449274012,
        "distance": 0.8428347743350184
      }
    },
    {},
    {},
    {
      "pillow": {
        "heading": 138.7159009233286,
        "distance": 1.757689420538766
      }
    },
    {},
    {
      "stairs": {
        "heading": 154.98566178128664,
        "distance": 1.729615452422424
      }
    },
    {
      "mattress": {
        "heading": -74.59067794492377,
        "distance": 0.8154696016590848
      }
    },
    {
      "mattress": {
        "heading": -136.1973544822377,
        "distance": 0.5755877646997092
      }
    },
    {
      "door": {
        "heading": -29.625111269760765,
        "distance": 1.9181893489093316
      }
    },
    {},
    {
      "table desk dresser": {
        "heading": -6.1394280684048965,
        "distance": 0.5205979125810067
      }
    },
    {},
    {},
    {},
    {},
    {
      "towel _ rack": {
        "heading": -16.366576103618087,
        "distance": 1.959485621799438
      }
    },
    {
      "bed": {
        "heading": 95.0384693061934,
        "distance": 0.5403152933678164
      }
    }
  ],
  "9e574409dd8f41419ddd6d06cb5c4dae": [
    {
      "pillow": {
        "heading": 155.58817903333926,
        "distance": 1.2192603521065224
      }
    },
    {
      "pillow": {
        "heading": -9.641245733269386,
        "distance": 0.9793404179206602
      }
    },
    {
      "pillow": {
        "heading": 127.30153000535978,
        "distance": 0.8119173418207346
      }
    },
    {},
    {
      "couch sofa sofa": {
        "heading": -143.50807205223742,
        "distance": 1.881242388629369
      }
    },
    {
      "table desk": {
        "heading": -3.85194103614495,
        "distance": 0.5379378082541416
      }
    },
    {
      "pillow": {
        "heading": -123.4319533051433,
        "distance": 1.9498549018567486
      }
    },
    {},
    {},
    {},
    {},
    {
      "couch sofa sofa": {
        "heading": -109.51432901811405,
        "distance": 1.8280488620420803
      }
    }
  ],
  "37f4e459dfa54aff98d84e8287138288": [
    {},
    {
      "chandelier chandelier": {
        "heading": 160.32274095043226,
        "distance": 0.6525735777971207
      }
    },
    {
      "couch sofa sofa": {
        "heading": -10.643740287330843,
        "distance": 0.7751549038409122
      }
    },
    {
      "chandelier chandelier": {
        "heading": -81.52659722472319,
        "distance": 1.5175459432321148
      }
    },
    {},
    {
      "stairs": {
        "heading": 158.77869078443473,
        "distance": 1.1443823366868733
      }
    },
    {},
    {
      "chandelier chandelier": {
        "heading": -134.1107287220574,
        "distance": 1.3524190630058914
      }
    },
    {},
    {},
    {
      "vent": {
        "heading": 83.88825119162152,
        "distance": 1.5665056182162103
      }
    },
    {},
    {
      "stairs": {
        "heading": -5.618078551018272,
        "distance": 1.2117767558275392
      }
    },
    {
      "vase footstool": {
        "heading": -125.03515219496498,
        "distance": 0.9918841125072346
      }
    },
    {
      "window": {
        "heading": 43.602940193618764,
        "distance": 1.233143316076165
      }
    },
    {
      "mirror": {
        "heading": -43.46245013411351,
        "distance": 1.2710081438921006
      }
    },
    {}
  ],
  "4ab7185168cc482bb745b7de90029bf3": [
    {
      "rug mattress": {
        "heading": -105.61294240279328,
        "distance": 0.526820369132043
      }
    },
    {},
    {
      "shelf cabinet bookcase shelf cabinet": {
        "heading": 150.08364303414493,
        "distance": 0.6810963710206748
      }
    },
    {
      "picture picture _ frame eye": {
        "heading": 119.4879775399616,
        "distance": 1.083604618310883
      }
    },
    {},
    {},
    {},
    {},
    {},
    {},
    {},
    {},
    {},
    {},
    {},
    {
      "rug": {
        "heading": 16.70783919480064,
        "distance": 1.6162664550100394
      }
    },
    {},
    {
      "window closet": {
        "heading": 52.17479551949404,
        "distance": 1.1152534838718684
      }
    },
    {},
    {},
    {},
    {},
    {},
    {
      "vent": {
        "heading": 112.92296230036328,
        "distance": 0.9642131215248044
      }
    },
    {},
    {},
    {},
    {},
    {},
    {},
    {},
    {},
    {},
    {},
    {
      "couch sofa sofa": {
        "heading": 5.185334287106798,
        "distance": 1.4124055543484304
      }
    },
    {}
  ],
  "9594700e2d354cc89c318b8df7ac29b1": [
    {},
    {
      "window": {
        "heading": 84.4361508338718,
        "distance": 1.0490990041470027
      }
    },
    {
      "window": {
        "heading": 157.36871713818056,
        "distance": 1.2746561768756461
      }
    },
    {},
    {},
    {},
    {
      "shelf cabinet shelf cabinet dresser": {
        "heading": 34.03522315965202,
        "distance": 1.97147306020331
      }
    },
    {
      "lamp": {
        "heading": -75.66917258759473,
        "distance": 1.857729976895452
      }
    },
    {},
    {},
    {},
    {},
    {},
    {},
    {}
  ],
  "fddca3fc457d4514a832025de148d6cd": [
    {},
    {
      "window": {
        "heading": 166.1975189299793,
        "distance": 1.1944595124771111
      }
    },
    {
      "pillow": {
        "heading": 176.35935085488302,
        "distance": 0.6755703350764
      }
    },
    {
      "pillow": {
        "heading": 47.70650200354493,
        "distance": 1.5790839348921648
      }
    },
    {
      "pillow": {
        "heading": -38.21250350461034,
        "distance": 0.6458049320833326
      }
    },
    {},
    {
      "towel towel rack": {
        "heading": -14.825241931919408,
        "distance": 1.2792409435642211
      }
    },
    {
      "shelf cabinet bookcase shelf cabinet dresser": {
        "heading": -169.27873623503325,
        "distance": 1.3610613098215174
      }
    },
    {
      "shelf cabinet shelf cabinet": {
        "heading": 66.17402700068558,
        "distance": 0.8511748436226907
      }
    },
    {},
    {},
    {
      "mirror painting painting": {
        "heading": 100.31194442278047,
        "distance": 0.9789469875477536
      }
    },
    {},
    {},
    {
      "bed mattress": {
        "heading": -25.758241531348403,
        "distance": 1.5306379542823496
      }
    },
    {},
    {},
    {},
    {},
    {},
    {
      "fridge door closet": {
        "heading": -116.89949688378181,
        "distance": 1.739578317921205
      }
    },
    {
      "curtain": {
        "heading": 81.36483290096493,
        "distance": 1.0854523795444302
      }
    },
    {
      "picture picture frame": {
        "heading": -135.76721191864743,
        "distance": 1.9042283481146673
      }
    },
    {
      "bed": {
        "heading": 31.284693872916108,
        "distance": 1.9612843180712036
      }
    },
    {
      "sofa sofa": {
        "heading": -47.7595691945308,
        "distance": 1.5835840324755728
      }
    },
    {
      "bed": {
        "heading": -14.8045634235595,
        "distance": 1.70034494707159
      }
    }
  ],
  "c6ee591e1061490d8c15ff8de1ab58aa": [
    {
      "rug": {
        "heading": 95.53959154342857,
        "distance": 1.6794122421583912
      }
    },
    {
      "clock": {
        "heading": 172.92948107884786,
        "distance": 0.8980782971874279
      }
    },
    {},
    {},
    {
      "rug": {
        "heading": -54.1653067259285,
        "distance": 1.4532810725009127
      }
    },
    {
      "couch sofa sofa": {
        "heading": 85.88815356894776,
        "distance": 1.2178232436746839
      }
    },
    {},
    {},
    {},
    {},
    {
      "chair armchair armchair": {
        "heading": 104.14251788262368,
        "distance": 0.7392161217578914
      }
    },
    {},
    {},
    {},
    {},
    {},
    {},
    {},
    {
      "pillow": {
        "heading": -155.08312051546972,
        "distance": 1.1895201690570045
      }
    },
    {
      "footstool ottoman": {
        "heading": -117.11526441395327,
        "distance": 1.8875038171299796
      }
    },
    {},
    {},
    {},
    {},
    {},
    {},
    {
      "window picture picture frame": {
        "heading": -123.17265311111603,
        "distance": 1.304025538291186
      }
    },
    {},
    {},
    {},
    {},
    {}
  ],
  "22fc81e0645a42d5be891f95327b4c62": [
    {
      "microwave": {
        "heading": 41.93397677744329,
        "distance": 1.3649070538468049
      }
    },
    {},
    {
      "footstool ottoman": {
        "heading": 6.999122996121628,
        "distance": 1.684375813648937
      }
    },
    {},
    {},
    {},
    {
      "rug mattress": {
        "heading": -143.43326708535065,
        "distance": 1.9543943220302888
      }
    },
    {
      "oven": {
        "heading": 16.411543505782504,
        "distance": 1.0995440948086925
      }
    },
    {},
    {},
    {},
    {
      "towel curtain": {
        "heading": -86.71999677698672,
        "distance": 0.6045098210565996
      }
    },
    {
      "door": {
        "heading": 168.5703163296962,
        "distance": 1.0372976568067345
      }
    },
    {},
    {}
  ],
  "f99835e3fffc45bbb3b4c992c78756e5": [
    {
      "pillow": {
        "heading": 171.12458544030278,
        "distance": 1.203856511365074
      }
    },
    {
      "couch sofa sofa": {
        "heading": 85.99339210867993,
        "distance": 0.5360598235902669
      }
    },
    {},
    {
      "shelf cabinet shelf cabinet": {
        "heading": 37.54938478287656,
        "distance": 0.8308694688869407
      }
    },
    {
      "rug massage table mattress": {
        "heading": -122.28645619659302,
        "distance": 1.8699557610509574
      }
    },
    {},
    {},
    {
      "pool table pool": {
        "heading": 145.9535667203574,
        "distance": 0.8538313054321722
      }
    },
    {},
    {
      "bookcase dresser": {
        "heading": 108.18188568575874,
        "distance": 0.8405521308310742
      }
    },
    {},
    {},
    {},
    {
      "eye _ chart plaque": {
        "heading": 151.04088500452832,
        "distance": 0.9956347382714761
      }
    },
    {},
    {}
  ],
  "9f140cae53d74624a23587631c8d0478": [
    {},
    {
      "towel towel _ rack": {
        "heading": -84.53575091741594,
        "distance": 1.8393082237639713
      }
    },
    {
      "towel": {
        "heading": 155.1179160846483,
        "distance": 1.5061600830202346
      }
    },
    {
      "pillow": {
        "heading": 132.26220139132556,
        "distance": 1.0373039185615502
      }
    },
    {
      "pillow": {
        "heading": -163.8816659776826,
        "distance": 1.270473927002489
      }
    },
    {
      "window": {
        "heading": -119.90096989872033,
        "distance": 1.1034897259034446
      }
    },
    {},
    {},
    {
      "couch bed sofa sofa": {
        "heading": 12.936302413847727,
        "distance": 1.3518307127434643
      }
    },
    {
      "stool footsto": {
        "heading": 170.95960806180307,
        "distance": 0.590356631891721
      }
    },
    {},
    {
      "shelf cabinet shelf cabinet": {
        "heading": 77.25371094371059,
        "distance": 1.733340997474595
      }
    },
    {
      "bed": {
        "heading": 148.90518111267278,
        "distance": 0.6538306013013695
      }
    },
    {
      "mattress": {
        "heading": 33.43548687376568,
        "distance": 1.1392632126827849
      }
    },
    {},
    {
      "towel": {
        "heading": -117.88681608536064,
        "distance": 1.0710966924575946
      }
    },
    {},
    {},
    {
      "door closet": {
        "heading": -97.85255737314748,
        "distance": 1.4292021263993853
      }
    },
    {
      "mattress": {
        "heading": 71.7962884099708,
        "distance": 1.307947211314427
      }
    },
    {
      "towel pillow": {
        "heading": 142.99521846412063,
        "distance": 1.7017345831123407
      }
    },
    {
      "towel": {
        "heading": -110.97358284541352,
        "distance": 1.710317047599219
      }
    },
    {},
    {
      "towel": {
        "heading": 17.694618045548935,
        "distance": 1.9435389641793666
      }
    },
    {
      "door closet": {
        "heading": 26.6118500189896,
        "distance": 1.7538481324912514
      }
    },
    {},
    {
      "bed": {
        "heading": 109.05820449554795,
        "distance": 1.8480039495296903
      }
    },
    {
      "bed mattress": {
        "heading": 8.405422285160114,
        "distance": 1.9364374340181427
      }
    },
    {
      "door": {
        "heading": 80.03568297738911,
        "distance": 0.5844147840903556
      }
    },
    {
      "shelf cabinet shelf cabinet": {
        "heading": 92.80483073887382,
        "distance": 1.2371878201831974
      }
    },
    {
      "towel _ rack": {
        "heading": -32.32159652181454,
        "distance": 1.6180669710626405
      }
    },
    {},
    {},
    {
      "table desk": {
        "heading": -68.47540239635067,
        "distance": 1.2658442729886938
      }
    },
    {
      "desk": {
        "heading": -135.08458765550992,
        "distance": 0.683977853378176
      }
    }
  ],
  "76f8ea642f5541cf80e93ba4d2430b7c": [
    {
      "chandelier chandelier": {
        "heading": -42.18432312366832,
        "distance": 1.1523505882235918
      }
    },
    {
      "rug": {
        "heading": -103.13155380701718,
        "distance": 0.9180687062481834
      }
    },
    {
      "shelf cabinet shelf cabinet dresser": {
        "heading": 18.024673082179646,
        "distance": 1.5945886527598505
      }
    },
    {},
    {
      "pillow": {
        "heading": 165.98651095304768,
        "distance": 0.5312671512340428
      }
    },
    {
      "couch sofa sofa": {
        "heading": -59.447609504437324,
        "distance": 1.6675852121203165
      }
    },
    {},
    {
      "pillow": {
        "heading": 140.1939197776739,
        "distance": 1.482572296815634
      }
    },
    {},
    {
      "couch sofa sofa": {
        "heading": 83.61063809960609,
        "distance": 0.6410290668037204
      }
    },
    {},
    {},
    {},
    {},
    {},
    {},
    {},
    {},
    {},
    {},
    {},
    {},
    {
      "mattress": {
        "heading": 134.76855891829456,
        "distance": 1.2107760867715527
      }
    },
    {},
    {
      "window": {
        "heading": -110.63544216030135,
        "distance": 1.4051072720752402
      }
    },
    {},
    {}
  ],
  "7bf81bd8601e4bde87ef2365f625288c": [
    {
      "shelf cabinet shelf cabinet": {
        "heading": 49.11849618946678,
        "distance": 1.710927059044789
      }
    },
    {
      "shelf cabinet shelf cabinet": {
        "heading": 77.73677649909428,
        "distance": 1.0923464131443599
      }
    },
    {
      "couch bed sofa sofa": {
        "heading": -132.02215544427264,
        "distance": 1.9289627304460537
      }
    },
    {
      "bed": {
        "heading": -81.34729889910857,
        "distance": 0.7220424116058464
      }
    },
    {
      "chandelier chandelier": {
        "heading": -157.21970985614334,
        "distance": 1.5726054848424023
      }
    },
    {
      "mattress": {
        "heading": -159.83568121622054,
        "distance": 1.8798299157788125
      }
    },
    {},
    {},
    {
      "rug pool _ table _ chart pool": {
        "heading": 135.5965696254965,
        "distance": 1.1130770013080804
      }
    },
    {},
    {},
    {
      "chair armchair armchair": {
        "heading": 93.61099308469824,
        "distance": 0.663269218584146
      }
    },
    {},
    {
      "chair armchair armchair": {
        "heading": 121.16241679026251,
        "distance": 0.6716799505424311
      }
    },
    {},
    {},
    {
      "table desk table": {
        "heading": 110.19275747361377,
        "distance": 0.8392889859673311
      }
    }
  ],
  "6d24c882111d4c29b64b6b494d644159": [
    {},
    {},
    {
      "chandelier chandelier": {
        "heading": -160.91587774056114,
        "distance": 1.4052434115003754
      }
    },
    {
      "couch sofa sofa": {
        "heading": 84.60712262958367,
        "distance": 1.854761698448963
      }
    },
    {},
    {
      "chandelier chandelier clock": {
        "heading": -39.21819385122603,
        "distance": 1.8103040642135952
      }
    },
    {},
    {
      "vase": {
        "heading": 129.31185066602131,
        "distance": 0.7520123898034261
      }
    },
    {
      "couch sofa seat sofa": {
        "heading": -62.352151627560275,
        "distance": 1.3692181137526225
      }
    },
    {},
    {},
    {},
    {},
    {},
    {},
    {
      "bookcase grill": {
        "heading": 88.40206330915822,
        "distance": 1.4922784261595043
      }
    },
    {
      "lamp": {
        "heading": 93.18234308290323,
        "distance": 1.011662240478508
      }
    },
    {},
    {},
    {
      "picture frame pool": {
        "heading": -79.09895011221683,
        "distance": 1.0691325736825463
      }
    },
    {},
    {
      "window": {
        "heading": 33.96775201462907,
        "distance": 1.7972949433188656
      }
    },
    {},
    {
      "window": {
        "heading": 120.70387108740783,
        "distance": 1.2073296961488724
      }
    },
    {}
  ],
  "720ca9c0b604445bab3bd731000bc5ca": [
    {},
    {},
    {},
    {},
    {},
    {},
    {},
    {
      "window": {
        "heading": 65.46705599415424,
        "distance": 0.7014193404548711
      }
    },
    {
      "towel": {
        "heading": -85.75683788354684,
        "distance": 1.1155564389388877
      }
    },
    {
      "shelf cabinet shelf cabinet": {
        "heading": 33.725488054344964,
        "distance": 1.1255183086205243
      }
    },
    {
      "lamp": {
        "heading": -129.35422384065816,
        "distance": 1.8118672240386975
      }
    },
    {},
    {
      "bed": {
        "heading": 168.13788150763185,
        "distance": 1.8085853841300816
      }
    },
    {
      "window picture": {
        "heading": -146.86140426201646,
        "distance": 1.5035404957247374
      }
    },
    {
      "lamp": {
        "heading": 16.313731600571117,
        "distance": 1.057939362395659
      }
    },
    {
      "shelf cabinet shelf cabinet": {
        "heading": -153.55842385983598,
        "distance": 0.8752741094811681
      }
    },
    {},
    {
      "picture frame eye _ chart clock": {
        "heading": -111.36010296114705,
        "distance": 1.3321095609740028
      }
    },
    {},
    {},
    {},
    {},
    {},
    {},
    {},
    {
      "lamp": {
        "heading": 55.22286976141436,
        "distance": 0.9423628086430158
      }
    },
    {}
  ],
  "d98247d9b9724eb9a730a1a5d9f1536a": [
    {},
    {
      "towel": {
        "heading": 121.11391645867388,
        "distance": 0.6709277484587822
      }
    },
    {
      "towel": {
        "heading": -129.040300447493,
        "distance": 1.6589647380406878
      }
    },
    {},
    {
      "towel": {
        "heading": -131.3812876612461,
        "distance": 1.4137940089382317
      }
    },
    {},
    {
      "pillow": {
        "heading": -85.18361051926097,
        "distance": 1.2565405799221274
      }
    },
    {
      "shelf cabinet shelf cabinet": {
        "heading": -153.83357487878345,
        "distance": 1.656817879661474
      }
    },
    {
      "shelf cabinet bookcase shelf cabinet": {
        "heading": 74.37773920196665,
        "distance": 1.39269043195696
      }
    },
    {
      "mattress": {
        "heading": -138.73944448561423,
        "distance": 1.356247751330894
      }
    },
    {
      "bed": {
        "heading": 53.616183236238925,
        "distance": 1.3156843265698703
      }
    },
    {},
    {
      "window": {
        "heading": -28.92054523809,
        "distance": 0.9710391817324955
      }
    },
    {
      "pillow": {
        "heading": 27.407307435576797,
        "distance": 1.349079925227822
      }
    },
    {},
    {},
    {
      "mattress": {
        "heading": 15.46957462812378,
        "distance": 1.6611425434328426
      }
    },
    {},
    {
      "picture _ frame eye _ chart clock": {
        "heading": -111.29648676229486,
        "distance": 1.6803651383400275
      }
    },
    {},
    {},
    {},
    {},
    {},
    {},
    {},
    {
      "mirror": {
        "heading": -158.9317545098053,
        "distance": 0.5305957175418761
      }
    },
    {
      "mattress": {
        "heading": -133.66712532357107,
        "distance": 1.6594758888681906
      }
    },
    {
      "desk dresser": {
        "heading": -100.706320843109,
        "distance": 1.8649734513829994
      }
    },
    {
      "mattress": {
        "heading": -30.575164454603907,
        "distance": 1.9509420304803653
      }
    },
    {},
    {},
    {
      "bed": {
        "heading": 51.34099921076634,
        "distance": 0.5028124051908176
      }
    },
    {
      "window": {
        "heading": -143.41653392629343,
        "distance": 1.2373859606529822
      }
    }
  ],
  "32bae6dbde3e465e9fde5ac4519fa157": [
    {
      "rug mattress": {
        "heading": 131.32582577605,
        "distance": 0.614005628923228
      }
    },
    {},
    {},
    {},
    {},
    {},
    {},
    {
      "chair armchair armchair": {
        "heading": -139.1646717800149,
        "distance": 0.9068922389831799
      }
    },
    {},
    {},
    {},
    {
      "door closet": {
        "heading": 174.85368518353766,
        "distance": 1.5467804908332168
      }
    },
    {
      "stairs": {
        "heading": -25.301234736009718,
        "distance": 1.7181345798040772
      }
    },
    {
      "window": {
        "heading": 49.858798983999264,
        "distance": 1.9296301760079932
      }
    },
    {},
    {},
    {},
    {},
    {
      "desk bar counter massage _ table": {
        "heading": -61.619600670760974,
        "distance": 0.8328064613247272
      }
    },
    {},
    {},
    {},
    {},
    {},
    {},
    {},
    {},
    {},
    {},
    {},
    {},
    {
      "vent": {
        "heading": -174.31226087482173,
        "distance": 0.8367438315383822
      }
    },
    {},
    {}
  ],
  "937ef6a5582f4186805e8f370131ddf3": [
    {
      "basket ottoman": {
        "heading": 167.68015262656536,
        "distance": 1.8698025762438708
      }
    },
    {
      "rug": {
        "heading": -50.744665012428385,
        "distance": 0.9447068140600503
      }
    },
    {},
    {
      "rug": {
        "heading": -157.17920277775036,
        "distance": 0.6832489415168926
      }
    },
    {},
    {},
    {},
    {},
    {},
    {},
    {},
    {
      "door": {
        "heading": 26.546796965917792,
        "distance": 1.6649409072691135
      }
    },
    {},
    {},
    {},
    {},
    {
      "shelf cabinet closet shelf cabinet": {
        "heading": -141.57292202405085,
        "distance": 0.5085614431136827
      }
    },
    {},
    {
      "grill": {
        "heading": 172.97739702611904,
        "distance": 0.694117921156364
      }
    },
    {},
    {},
    {},
    {},
    {}
  ],
  "5e088d1a1343492fa42091aebe7f9e04": [
    {
      "chandelier chandelier": {
        "heading": 111.22138915248951,
        "distance": 1.547302341418717
      }
    },
    {},
    {
      "shelf cabinet shelf cabinet": {
        "heading": -33.16168430996001,
        "distance": 1.0195782033706613
      }
    },
    {
      "chandelier chandelier": {
        "heading": 24.942957542641466,
        "distance": 1.7832718011495197
      }
    },
    {
      "rug": {
        "heading": -172.25234368942026,
        "distance": 1.610835890233372
      }
    },
    {},
    {},
    {},
    {},
    {},
    {
      "rug": {
        "heading": 38.579091297570216,
        "distance": 0.9757630678265117
      }
    },
    {},
    {
      "vent": {
        "heading": 89.2780289976464,
        "distance": 1.5196700565672694
      }
    },
    {
      "door": {
        "heading": 104.18963452443973,
        "distance": 0.5228381851581436
      }
    },
    {},
    {},
    {},
    {
      "fridge": {
        "heading": -152.36020199498813,
        "distance": 1.1763315118985798
      }
    },
    {}
  ],
  "7458e0a2cb7e4ce3b7c85fe452ac4dbc": [
    {},
    {
      "lamp chandelier chandelier clock": {
        "heading": -132.28393151604593,
        "distance": 1.8165044507707908
      }
    },
    {
      "shelf cabinet bookcase shelf cabinet": {
        "heading": -94.4365316074565,
        "distance": 1.6951684511872416
      }
    },
    {
      "rug mattress": {
        "heading": -156.4985415224365,
        "distance": 1.70706216102853
      }
    },
    {},
    {
      "painting picture picture frame painting": {
        "heading": 111.6455232352464,
        "distance": 1.4459644554251585
      }
    },
    {
      "painting picture picture frame painting": {
        "heading": -21.642926449359436,
        "distance": 1.9778630665273718
      }
    },
    {
      "shelf cabinet shelf cabinet": {
        "heading": -18.470033089415494,
        "distance": 0.9014316009105692
      }
    },
    {
      "grill": {
        "heading": -61.00511899417201,
        "distance": 0.89153602910088
      }
    },
    {
      "vase": {
        "heading": 75.64052604035959,
        "distance": 1.095508085059844
      }
    },
    {},
    {},
    {},
    {},
    {},
    {
      "desk counter": {
        "heading": -120.45284671729965,
        "distance": 1.9311753573228518
      }
    },
    {},
    {},
    {}
  ],
  "796a7cec3a9648a097bfe3a76587513f": [
    {},
    {},
    {},
    {
      "rug": {
        "heading": 166.08545170213068,
        "distance": 1.5507293987637838
      }
    },
    {
      "pillow": {
        "heading": 40.94869908413378,
        "distance": 1.9877738144478887
      }
    },
    {},
    {
      "rug": {
        "heading": -11.209938537542854,
        "distance": 1.4497988314407717
      }
    },
    {
      "pillow": {
        "heading": 48.54658194842534,
        "distance": 0.6899094467947176
      }
    },
    {},
    {
      "door closet": {
        "heading": 47.26521644146075,
        "distance": 1.0746423176859272
      }
    },
    {
      "armchair seat armchair": {
        "heading": -92.8582365303913,
        "distance": 1.4601419989181967
      }
    },
    {
      "pillow": {
        "heading": -177.11083589531566,
        "distance": 1.4122934479174325
      }
    },
    {},
    {},
    {},
    {},
    {},
    {},
    {},
    {
      "rug": {
        "heading": 44.12661407576945,
        "distance": 1.1376554059987802
      }
    },
    {},
    {},
    {
      "table desk": {
        "heading": -41.30350200590641,
        "distance": 1.6778325969563768
      }
    },
    {
      "table desk table massage _ table": {
        "heading": 8.297552295541607,
        "distance": 1.9809180744489454
      }
    },
    {},
    {},
    {},
    {},
    {},
    {
      "pillow": {
        "heading": -8.212493572901337,
        "distance": 1.5386148168913796
      }
    }
  ],
  "7efd4325cb7f42519c11210ffa7a7e1c": [
    {
      "pillow": {
        "heading": -127.26496960454361,
        "distance": 1.6804503154734194
      }
    },
    {
      "pillow": {
        "heading": 38.98628984344083,
        "distance": 1.2322706888452917
      }
    },
    {
      "pillow": {
        "heading": -113.93836533561942,
        "distance": 1.2096737713753454
      }
    },
    {},
    {},
    {
      "door": {
        "heading": 117.91121247069304,
        "distance": 1.7553298893646474
      }
    },
    {
      "rug": {
        "heading": -74.67626705975053,
        "distance": 0.6019955492377365
      }
    },
    {
      "pillow": {
        "heading": 128.03403958028179,
        "distance": 0.5560985776399132
      }
    },
    {},
    {
      "statue statue": {
        "heading": 112.42874777685415,
        "distance": 1.3502498463348938
      }
    },
    {
      "pillow": {
        "heading": -31.916060905850372,
        "distance": 0.5593768849401226
      }
    },
    {},
    {},
    {},
    {},
    {},
    {
      "pillow": {
        "heading": 143.7215682497167,
        "distance": 1.3297361331751802
      }
    },
    {
      "pillow": {
        "heading": 178.17890472448852,
        "distance": 0.8543825384336912
      }
    },
    {
      "shelf cabinet shelf cabinet": {
        "heading": 108.14448409453655,
        "distance": 1.0076603106677513
      }
    },
    {},
    {
      "window": {
        "heading": -57.59381085396278,
        "distance": 0.8965836022668439
      }
    },
    {
      "pillow": {
        "heading": -102.24161608519056,
        "distance": 0.8228129338739945
      }
    },
    {
      "pillow": {
        "heading": 112.79177478785698,
        "distance": 1.4537604839639584
      }
    },
    {
      "pillow": {
        "heading": -3.744169419226722,
        "distance": 0.82678589469134
      }
    },
    {},
    {
      "rug": {
        "heading": -131.0608893721609,
        "distance": 1.428128467703716
      }
    },
    {},
    {},
    {},
    {
      "rug pool": {
        "heading": 10.075958665739165,
        "distance": 0.7732448463524983
      }
    },
    {},
    {},
    {},
    {},
    {}
  ],
  "fa51cb2051f240d795737cdffeda6178": [
    {},
    {},
    {
      "stairs": {
        "heading": -150.80015601657158,
        "distance": 0.5667202069693902
      }
    },
    {
      "door": {
        "heading": 80.73337433098999,
        "distance": 1.6692216351213878
      }
    }
  ],
  "b9152c697f4c4a2fb4eef96ed220b484": [
    {},
    {},
    {},
    {
      "picture picture _ frame": {
        "heading": -87.91296726996727,
        "distance": 1.6904319376806536
      }
    },
    {
      "shelf cabinet bookcase shelf cabinet": {
        "heading": -34.95771820672229,
        "distance": 0.606740406535365
      }
    },
    {},
    {},
    {
      "curtain pillow": {
        "heading": -113.10697453545659,
        "distance": 0.9214987242197696
      }
    },
    {},
    {},
    {
      "rug pool table massage _ table mattress": {
        "heading": -93.48738176749384,
        "distance": 1.1488352082772475
      }
    },
    {},
    {
      "rug massage _ table mattress": {
        "heading": 69.62561006400793,
        "distance": 1.9870135031980976
      }
    },
    {},
    {
      "desk": {
        "heading": -170.77063583669985,
        "distance": 1.1901396486386926
      }
    },
    {},
    {},
    {
      "counter": {
        "heading": -98.09802053699084,
        "distance": 0.9892190757153541
      }
    },
    {},
    {},
    {},
    {},
    {},
    {
      "bookcase dresser": {
        "heading": -141.90662047219266,
        "distance": 0.734478714948388
      }
    }
  ],
  "f3fb79361ba64ba3b4d5c2160f4d4f1f": [
    {
      "couch sofa sofa": {
        "heading": -49.19860562842865,
        "distance": 1.9433517267609721
      }
    },
    {
      "picture picture frame plaque": {
        "heading": 86.7289817711756,
        "distance": 1.516957560627718
      }
    },
    {},
    {
      "door": {
        "heading": 100.76069917491952,
        "distance": 1.4550819842417164
      }
    },
    {},
    {},
    {
      "curtain": {
        "heading": -119.76791720908034,
        "distance": 0.9903528231027776
      }
    },
    {},
    {
      "bathtub": {
        "heading": 176.1916246154168,
        "distance": 0.7439070073764851
      }
    },
    {}
  ],
  "2e9912cb8d1842f88aff7bb59bdcbf5d": [
    {
      "couch sofa sofa": {
        "heading": -67.04808278985026,
        "distance": 0.7606731396619435
      }
    },
    {
      "door closet": {
        "heading": -140.98609493830338,
        "distance": 1.0181886154111388
      }
    },
    {
      "door closet": {
        "heading": 13.268080705866112,
        "distance": 1.771182035473884
      }
    },
    {},
    {
      "mattress": {
        "heading": -78.93875149425865,
        "distance": 1.378952958546848
      }
    },
    {}
  ],
  "e40675d8209d426e8f60cdd315953cab": [
    {
      "couch sofa sofa": {
        "heading": 33.36615737037897,
        "distance": 1.9704747058633636
      }
    },
    {},
    {
      "pillow": {
        "heading": 21.840375101789306,
        "distance": 1.1143147605489598
      }
    },
    {},
    {},
    {
      "couch sofa sofa": {
        "heading": 146.7983151959894,
        "distance": 0.8729095855583409
      }
    },
    {},
    {
      "chandelier chandelier": {
        "heading": 55.288455421924255,
        "distance": 1.3626953263087258
      }
    },
    {
      "shelf cabinet shelf cabinet": {
        "heading": -130.4853313072992,
        "distance": 0.6556788675623153
      }
    },
    {},
    {},
    {
      "door": {
        "heading": 169.41597582445974,
        "distance": 1.202674924865487
      }
    },
    {},
    {
      "picture pool": {
        "heading": 132.36358279295627,
        "distance": 1.2236535956851324
      }
    },
    {},
    {
      "lamp": {
        "heading": 53.74054052946664,
        "distance": 1.6821486113846764
      }
    },
    {
      "ottoman": {
        "heading": -157.1446179960207,
        "distance": 1.004887616080826
      }
    },
    {
      "mirror window": {
        "heading": -90.80810092629838,
        "distance": 0.6479624782582137
      }
    }
  ],
  "a5f020c705db447cabdb237e7b7027fe": [
    {
      "footstool ottoman": {
        "heading": 33.829138238319956,
        "distance": 0.8805079069076645
      }
    },
    {},
    {
      "microwave": {
        "heading": 31.75754315018537,
        "distance": 1.8005733878021626
      }
    },
    {
      "footstool ottoman": {
        "heading": 117.34667964755471,
        "distance": 0.7441447241698147
      }
    },
    {
      "shelf cabinet shelf cabinet": {
        "heading": 158.04250028177438,
        "distance": 1.4790640374342054
      }
    },
    {},
    {
      "shelf cabinet shelf cabinet": {
        "heading": 56.87564041675523,
        "distance": 1.5462964767953788
      }
    },
    {
      "fridge": {
        "heading": 113.97395294782473,
        "distance": 1.1555468432552751
      }
    },
    {
      "shelf cabinet shelf cabinet": {
        "heading": -9.389792005084502,
        "distance": 0.577578414123322
      }
    },
    {
      "towel": {
        "heading": -0.16640109512067625,
        "distance": 0.8227848865800619
      }
    },
    {
      "shelf cabinet shelf cabinet": {
        "heading": 177.17098837304133,
        "distance": 1.354724722458249
      }
    },
    {},
    {},
    {},
    {
      "shelf cabinet shelf cabinet": {
        "heading": 12.131198485206198,
        "distance": 1.5263937593002166
      }
    },
    {},
    {
      "shelf cabinet shelf cabinet": {
        "heading": -68.38520736528459,
        "distance": 1.5990389209956792
      }
    },
    {
      "towel towel": {
        "heading": 104.42437618728746,
        "distance": 1.0835486772148877
      }
    },
    {},
    {},
    {
      "shelf cabinet shelf cabinet": {
        "heading": 50.3218844439393,
        "distance": 0.5474802432504388
      }
    },
    {},
    {
      "pillow": {
        "heading": -132.78654566254164,
        "distance": 1.9725279220729353
      }
    },
    {
      "pool": {
        "heading": 161.7407104723024,
        "distance": 1.573722390494088
      }
    },
    {},
    {},
    {},
    {
      "fridge": {
        "heading": 170.81064340446113,
        "distance": 1.7037063382168325
      }
    }
  ],
  "d5dbd24d1b9c404a9b4fc687ecf17a4f": [
    {
      "clock": {
        "heading": 85.23853979125181,
        "distance": 0.5601439627008551
      }
    },
    {
      "shelf cabinet bookcase shelf cabinet": {
        "heading": -155.56732990292286,
        "distance": 1.1521458334056471
      }
    },
    {},
    {},
    {},
    {},
    {},
    {},
    {},
    {},
    {}
  ],
  "eac917cfb08842be82d8f5455434f74b": [
    {
      "chandelier chandelier": {
        "heading": -125.52243954658363,
        "distance": 0.722118631915132
      }
    },
    {},
    {
      "door": {
        "heading": -110.99899092639073,
        "distance": 1.1986638247818844
      }
    },
    {},
    {
      "footstool": {
        "heading": -146.3086060020871,
        "distance": 1.2466581228020974
      }
    },
    {},
    {},
    {
      "stairs": {
        "heading": -92.20995042286705,
        "distance": 1.0033766271127902
      }
    },
    {},
    {}
  ],
  "14628aaead7d4d6b97153bbd84cc6ef1": [
    {
      "chandelier chandelier": {
        "heading": -22.348507921286085,
        "distance": 0.7960054577509212
      }
    },
    {},
    {},
    {},
    {},
    {},
    {},
    {},
    {},
    {},
    {},
    {
      "lamp": {
        "heading": 147.98303204192325,
        "distance": 1.8117427881824126
      }
    },
    {}
  ],
  "466de00abb3346119a44dff5cdca68ba": [
    {
      "chandelier chandelier": {
        "heading": 92.33309681914113,
        "distance": 1.3633600769053142
      }
    },
    {
      "stairs": {
        "heading": -83.37995845222594,
        "distance": 1.647062166266108
      }
    },
    {},
    {},
    {},
    {
      "window": {
        "heading": 128.7969063626661,
        "distance": 0.937257544953158
      }
    },
    {},
    {},
    {
      "vent": {
        "heading": -125.93210126290549,
        "distance": 1.4809153325292885
      }
    },
    {},
    {},
    {
      "vent": {
        "heading": -113.10337083428695,
        "distance": 1.9597536935548363
      }
    },
    {},
    {},
    {},
    {}
  ],
  "276d365e9e6b42e6bb17571e9dfd2663": [
    {},
    {},
    {},
    {},
    {
      "painting picture picture painting": {
        "heading": -44.40917214247543,
        "distance": 1.5201233697379644
      }
    },
    {
      "rug": {
        "heading": -107.46422629707706,
        "distance": 1.867865042899782
      }
    },
    {
      "basket": {
        "heading": -103.10334713919798,
        "distance": 0.6041274385722564
      }
    },
    {},
    {},
    {
      "lamp chandelier chandelier": {
        "heading": 143.09986555483033,
        "distance": 1.5037407601311066
      }
    },
    {},
    {
      "rug": {
        "heading": -22.320128578097354,
        "distance": 1.2365713503371971
      }
    },
    {},
    {},
    {
      "lamp chandelier chandelier": {
        "heading": -53.497935332438814,
        "distance": 1.8109318587852765
      }
    },
    {},
    {},
    {
      "fridge": {
        "heading": 139.34326203241682,
        "distance": 1.7126986691158315
      }
    },
    {
      "lamp": {
        "heading": -58.52993383320491,
        "distance": 1.265359459173884
      }
    },
    {},
    {},
    {},
    {}
  ],
  "a5e69ef92c7b4b8d9804a444e919e230": [
    {},
    {
      "picture picture _ frame": {
        "heading": 69.3881703725381,
        "distance": 1.6381030799810297
      }
    },
    {},
    {},
    {},
    {},
    {},
    {
      "chandelier chandelier": {
        "heading": 146.51027719051132,
        "distance": 1.3712306957981253
      }
    },
    {},
    {},
    {},
    {},
    {},
    {},
    {
      "mattress": {
        "heading": 25.92005372911342,
        "distance": 1.5875566919438042
      }
    },
    {},
    {},
    {},
    {},
    {
      "door": {
        "heading": -63.78241875021824,
        "distance": 0.539314507770674
      }
    },
    {},
    {},
    {},
    {},
    {},
    {},
    {},
    {},
    {},
    {},
    {},
    {},
    {},
    {},
    {
      "painting painting": {
        "heading": -144.6698807042859,
        "distance": 1.4574664609798083
      }
    }
  ],
  "333d8508b2854c169ecdfa509cb0f068": [
    {},
    {
      "stairs": {
        "heading": 82.5620431104494,
        "distance": 0.6201747885191784
      }
    },
    {
      "stairs": {
        "heading": -41.697325094346354,
        "distance": 1.0462020791760147
      }
    },
    {},
    {
      "couch sofa sofa": {
        "heading": -17.38595254215221,
        "distance": 0.65204568258063
      }
    },
    {
      "console _ table": {
        "heading": -83.26955044526736,
        "distance": 1.1820433294411774
      }
    },
    {},
    {
      "door": {
        "heading": -173.11131316243294,
        "distance": 1.5161386528750243
      }
    },
    {
      "fridge": {
        "heading": -43.98653373850772,
        "distance": 0.6585922703970228
      }
    }
  ],
  "12c934ed973740efbdbe207ab3a064d3": [
    {},
    {},
    {},
    {
      "couch sofa sofa": {
        "heading": -142.211742116781,
        "distance": 1.7186390516689447
      }
    },
    {
      "stairs": {
        "heading": 129.59519904150847,
        "distance": 0.8699891265141833
      }
    },
    {
      "chair armchair armchair": {
        "heading": -21.888550863704438,
        "distance": 0.6333852761899899
      }
    },
    {},
    {},
    {
      "shelf cabinetcase closet shelf cabinet": {
        "heading": -52.02281861413172,
        "distance": 1.6351105804563706
      }
    },
    {},
    {},
    {
      "chair armchair armchair": {
        "heading": -25.97216077292046,
        "distance": 1.759295100684343
      }
    },
    {},
    {},
    {},
    {},
    {}
  ],
  "38b310ec74a041c3ba46b304a712d70f": [
    {},
    {
      "lamp": {
        "heading": 85.14877980999546,
        "distance": 1.8789449320757445
      }
    },
    {
      "mattress": {
        "heading": 142.73209044900278,
        "distance": 1.5100761802380267
      }
    },
    {},
    {
      "bed mattress": {
        "heading": 128.50456731629788,
        "distance": 1.0290601498968002
      }
    },
    {
      "pillow": {
        "heading": -0.37393791271333043,
        "distance": 1.0195473377453887
      }
    },
    {},
    {
      "couch bed": {
        "heading": 116.64329127468608,
        "distance": 1.3816890710093965
      }
    },
    {
      "window": {
        "heading": 153.03367667596842,
        "distance": 0.9199727552275856
      }
    },
    {},
    {},
    {},
    {},
    {
      "bed": {
        "heading": 0.9698295655661582,
        "distance": 1.4603750654415402
      }
    },
    {},
    {
      "picture picture frame": {
        "heading": 113.02036827624977,
        "distance": 1.0222695863343008
      }
    },
    {
      "mirror": {
        "heading": 174.73667349349466,
        "distance": 1.3642336376193136
      }
    },
    {},
    {
      "lamp": {
        "heading": -73.27271352162383,
        "distance": 0.6774028699194249
      }
    },
    {},
    {},
    {
      "door closet": {
        "heading": 60.19954946174599,
        "distance": 1.8314087241649002
      }
    },
    {},
    {
      "window picture": {
        "heading": -145.42748518931285,
        "distance": 1.1504229429621053
      }
    },
    {
      "mattress": {
        "heading": -127.13681175799407,
        "distance": 1.1585193908483533
      }
    },
    {
      "bookcase": {
        "heading": -84.41832743184167,
        "distance": 1.4664651936397126
      }
    },
    {
      "lamp": {
        "heading": 28.891966145387755,
        "distance": 1.548345996602379
      }
    },
    {
      "shelf cabinet shelf cabinet": {
        "heading": 123.56183951743736,
        "distance": 0.8632539491561717
      }
    },
    {},
    {},
    {
      "bookcase": {
        "heading": 163.96436516909716,
        "distance": 0.9808532817023894
      }
    }
  ],
  "c923f6e9440146129bef546a6fae0383": [
    {},
    {
      "window": {
        "heading": 31.733572472597785,
        "distance": 1.8898469196827947
      }
    },
    {},
    {
      "shelf cabinet bookcase shelf cabinet dresser": {
        "heading": -74.56314679291022,
        "distance": 1.741019337825538
      }
    },
    {
      "mattress": {
        "heading": -148.1502173904586,
        "distance": 1.5372109706376447
      }
    },
    {},
    {},
    {},
    {},
    {},
    {
      "towel": {
        "heading": -166.52068744674895,
        "distance": 1.3747823836754842
      }
    },
    {},
    {},
    {
      "towel": {
        "heading": -164.95966863677276,
        "distance": 1.587695159246534
      }
    },
    {},
    {
      "lamp": {
        "heading": 27.932814776565124,
        "distance": 1.2491505991221805
      }
    },
    {},
    {},
    {},
    {},
    {
      "window picture": {
        "heading": 41.16770905273256,
        "distance": 0.8494865697357438
      }
    },
    {},
    {},
    {},
    {
      "microwave": {
        "heading": 58.504451960401525,
        "distance": 0.6878507107964169
      }
    }
  ],
  "6e6c35e0ed8343a18a5999c5e27dd656": [
    {},
    {},
    {
      "couch bed sofa sofa": {
        "heading": -135.13055197912462,
        "distance": 1.7817192089932947
      }
    },
    {
      "shelf cabinet shelf cabinet": {
        "heading": 22.510852658290673,
        "distance": 1.1048727699383787
      }
    },
    {},
    {},
    {
      "mirror": {
        "heading": -6.728657869373819,
        "distance": 1.690664812358071
      }
    },
    {},
    {},
    {},
    {
      "mattress": {
        "heading": -4.625296505719945,
        "distance": 1.1099093818742212
      }
    },
    {},
    {},
    {
      "shelf cabinet shelf cabinet dresser": {
        "heading": -9.825434255862803,
        "distance": 1.1863448414475626
      }
    },
    {
      "towel footol ottoman": {
        "heading": -103.28294459783663,
        "distance": 0.6511098681555677
      }
    },
    {
      "grill": {
        "heading": 35.720206227911774,
        "distance": 1.4897994545237432
      }
    },
    {},
    {
      "pillow": {
        "heading": 153.78612734653063,
        "distance": 0.565708498434655
      }
    },
    {
      "picture _ frame eye _ chart": {
        "heading": 108.65491969040119,
        "distance": 1.7480965263067434
      }
    },
    {},
    {},
    {},
    {
      "bed": {
        "heading": -76.08374836685005,
        "distance": 1.1162284813713605
      }
    },
    {},
    {
      "door": {
        "heading": 30.98477010029245,
        "distance": 0.8529228883918316
      }
    },
    {},
    {},
    {},
    {
      "window": {
        "heading": 136.5380784746984,
        "distance": 1.7697499150205231
      }
    },
    {
      "mirror window": {
        "heading": 81.74919183255321,
        "distance": 1.5516401085877751
      }
    }
  ],
  "d1ca17ceba9045d8b65ac93f8d3cdaf1": [
    {
      "bathtub pool": {
        "heading": 88.98611384433286,
        "distance": 1.3886802151010218
      }
    },
    {
      "couch sofa sofa": {
        "heading": -29.460395315591626,
        "distance": 1.987164260982335
      }
    },
    {
      "lamp chandelier chandelier": {
        "heading": 10.914334220464468,
        "distance": 1.3743295029041032
      }
    },
    {
      "door": {
        "heading": -77.8508610076428,
        "distance": 1.7352906312648853
      }
    },
    {}
  ],
  "7e25da3804064036b06f806caf9f1e62": [
    {
      "rug": {
        "heading": 84.32717142294564,
        "distance": 1.9573134834499732
      }
    },
    {},
    {
      "pillow": {
        "heading": -124.87451932185562,
        "distance": 1.9469460967648455
      }
    },
    {},
    {},
    {},
    {},
    {
      "picture picture frame": {
        "heading": 40.055284491424715,
        "distance": 0.7647150106102696
      }
    },
    {},
    {},
    {},
    {},
    {},
    {
      "shelf cabinet shelf cabinet dresser": {
        "heading": 175.74525417924582,
        "distance": 1.3020983731313263
      }
    },
    {},
    {
      "window picture": {
        "heading": -52.46708714560022,
        "distance": 0.746120785772534
      }
    },
    {},
    {
      "vent": {
        "heading": 4.189971743358512,
        "distance": 1.7942624315432922
      }
    },
    {},
    {
      "couch sofa sofa": {
        "heading": 69.60404671115165,
        "distance": 0.5902194743901583
      }
    },
    {},
    {},
    {
      "door closet": {
        "heading": -171.33162957613922,
        "distance": 0.7717363509291004
      }
    },
    {},
    {},
    {},
    {
      "candle": {
        "heading": -74.05178775031881,
        "distance": 1.7517797315058794
      }
    },
    {
      "couch sofa sofa": {
        "heading": 7.418250382688143,
        "distance": 1.5473661538372552
      }
    },
    {},
    {},
    {},
    {},
    {},
    {},
    {},
    {},
    {},
    {},
    {}
  ]
}